curvedpy/__init__.py
curvedpy/conversions.py
curvedpy/geodesic_integrator_isotropic_xyz.py
curvedpy/geodesic_integrator_schwarzschild.py
curvedpy/geodesic_integrator_schwarzschild_prev_method.py
curvedpy/interpolation.py
curvedpy/old_SchwarzschildGeodesic.py
curvedpy/old_conversions.py
curvedpy/old_geodesic_integrator.py
curvedpy/utils.py
curvedpy/cameras/__init__.py
curvedpy/cameras/camera.py
curvedpy/geodesics/__init__.py
curvedpy/geodesics/blackhole.py
curvedpy/geodesics/blackhole_integrators/__init__.py
curvedpy/geodesics/blackhole_integrators/kerr_SPH.py
curvedpy/geodesics/blackhole_integrators/schwarzschild_XYZ.py
curvedpy/geodesics/blackhole_integrators/special/__init__.py
curvedpy/geodesics/blackhole_integrators/special/geodesic_integrator_isotropic_xyz.py
curvedpy/geodesics/blackhole_integrators/special/geodesic_integrator_schwarzschild.py
curvedpy/geodesics/blackhole_integrators/special/geodesic_integrator_schwarzschild_XYZ_derived.py
curvedpy/geodesics/blackhole_integrators/special/geodesic_integrator_schwarzschild_prev_method.py
curvedpy/metrics/__init__.py
curvedpy/metrics/kerr_bl.py
curvedpy/metrics/schwarzschild.py
curvedpy/metrics/schwarzschild_cart.py
curvedpy/utils/__init__.py
curvedpy/utils/conversions.py
curvedpy/utils/interpolation.py
curvedpy/utils/utils.py
curvedpy-0.0.3.dist-info/LICENSE
curvedpy-0.0.3.dist-info/METADATA
curvedpy-0.0.3.dist-info/WHEEL
curvedpy-0.0.3.dist-info/top_level.txt
curvedpy-0.0.3.dist-info/RECORD
