Metadata-Version: 2.1
Name: curvedpy
Version: 0.0.3
Summary: General Relativistic Geodesic Integrator
Home-page: https://github.com/bldevries/curvedpy
Author: B.L. de Vries
Author-email: <bldevries@protonmail.com>
License: GPL-3.0
Keywords: python,relativistic,ray,tracer,blackhole,astronomy,physics,numerical
Platform: UNKNOWN
Classifier: Development Status :: 3 - Alpha
Classifier: Intended Audience :: Education
Classifier: Programming Language :: Python :: 3
Classifier: Operating System :: MacOS :: MacOS X
Classifier: Operating System :: Microsoft :: Windows
License-File: LICENSE
Requires-Dist: numpy>=2.0.2
Requires-Dist: scipy>=1.13.1
Requires-Dist: sympy>=1.13.3
Requires-Dist: multiprocess>=0.70.17
